{
  "nomeCompleto": "Conocybe tenera",
  "autore": "(Schaeff.) Kühner 1935",
  "filogenesi": "regno: Fungi > phylum: Basidiomycota > classe: Agaricomycetes > ordine: Agaricales > famiglia: Bolbitiaceae",
  "nomeCorrente": null,
  "autoreCorrente": null,
  "campioniRaccolti": [
    {
      "collectionDate": "2025-07-07",
      "collector": "Antonio Guana",
      "locality": "Colle Palazzo, Oltressenda Alta",
      "localityCoordinates": "45.938839, 9.973808",
      "habitat": "Bosco misto abete e latifoglie",
      "determiner": "Pierino Bigoni"
    }
  ],
  "campioniExsiccata": [],
  "fenologia": {
    "raccoltaPiuPrecoce": "07/07",
    "raccoltaPiuTarda": "07/07",
    "campioniPerMese": [
      {
        "gen": 0
      },
      {
        "feb": 0
      },
      {
        "mar": 0
      },
      {
        "apr": 0
      },
      {
        "mag": 0
      },
      {
        "giu": 0
      },
      {
        "lug": 1
      },
      {
        "ago": 0
      },
      {
        "set": 0
      },
      {
        "ott": 0
      },
      {
        "nov": 0
      },
      {
        "dic": 0
      }
    ]
  },
  "statistiche": {
    "totaleCampioni": 1,
    "campioniRaccolti": 1,
    "campioniExsiccata": 0
  }
}